[
    {
        "title": "舞曲歌辭：吳俞兒舞歌：劍俞",
        "author": "陸龜蒙",
        "biography": "",
        "paragraphs": [
            "枝月喉，棹霜脊，北斗離離在寒碧。龍魂清，虎尾白，"
        ],
        "notes": [
            ""
        ],
        "volume": "卷二十二",
        "no#": 1
    },
    {
        "title": "舞曲歌辭：吳俞兒舞歌：矛俞",
        "author": "陸龜蒙",
        "biography": "",
        "paragraphs": [
            "手盤風，頭背分，電光戰扇，欲刺敲心留半線。",
            "纏肩繞脰，dl合眩旋，卓植赴列，奪避中節。",
            "前沖函禮穴，上指孛彗滅，與君一用來有截。"
        ],
        "notes": [
            ""
        ],
        "volume": "卷二十二",
        "no#": 2
    },
    {
        "title": "舞曲歌辭：吳俞兒舞歌：弩俞",
        "author": "陸龜蒙",
        "biography": "",
        "paragraphs": [
            "牛來開弦，人為置鏃。捩機關，迸山谷。鹿駭澀，"
        ],
        "notes": [
            ""
        ],
        "volume": "卷二十二",
        "no#": 3
    },
    {
        "title": "舞曲歌辭：東海有勇婦",
        "author": "李白",
        "biography": "",
        "paragraphs": [
            "梁山感杞妻，慟器為之傾。金石忽暫開，都由激深情。",
            "東海有勇婦，何慚蘇子卿。學劍越處子，超騰若流星。",
            "捐軀報夫仇，萬死不顧生。白刃耀素雪，蒼天感精誠。",
            "十步兩躩躍，三呼一交兵。斬首掉國門，蹴踏五藏行。",
            "割此伉儷憤，粲然大義明。北海李使君，飛章奏天庭。",
            "舍罪警風俗，流芳播滄瀛。志在列女籍，行帛已光榮。",
            "淳於免詔獄，漢主為緹縈。津妾一棹歌，脫父于嚴刑。",
            "十子若不肖，不如一女英。豫讓斬空衣，有心竟無成。",
            "要離殺慶忌，壯夫素所輕。妻子亦何辜，焚之買虛名。",
            "豈如東海婦，事立獨揚名。"
        ],
        "notes": [
            ""
        ],
        "volume": "卷二十二",
        "no#": 4
    },
    {
        "title": "舞曲歌辭：章和二年中",
        "author": "李賀",
        "biography": "",
        "paragraphs": [
            "雲蕭索，風拂拂，麥芒如篲黍和粟。關中父老百領襦，",
            "殷勤為我下田鉏，百錢攜賞絲桐客。遊春漫光塢花白，"
        ],
        "notes": [
            ""
        ],
        "volume": "卷二十二",
        "no#": 5
    },
    {
        "title": "舞曲歌辭：公莫舞歌",
        "author": "李賀",
        "biography": "",
        "paragraphs": [
            "方花古礎排九楹，刺豹淋血盛銀罌。華筵鼓吹無桐竹，",
            "腰下三看寶玦光，項莊掉箾攔前起。材官小臣公莫舞，",
            "鐵樞鐵楗重束關，大旗五丈撞雙環。漢王今日須秦印，"
        ],
        "notes": [
            ""
        ],
        "volume": "卷二十二",
        "no#": 6
    },
    {
        "title": "舞曲歌辭：拂舞辭",
        "author": "李賀",
        "biography": "",
        "paragraphs": [
            "吳娥聲絕天，空雲閑裴回。門外滿車馬，亦須生綠苔。",
            "尊有烏程酒，勸君千萬壽。全勝漢武錦樓上，",
            "丹成作蛇乘白霧，千年重化玉井龜。從蛇作龜二千載。",
            "吳堤綠草年年在。背有八卦稱神仙，邪鱗頑甲滑腥涎。"
        ],
        "notes": [
            ""
        ],
        "volume": "卷二十二",
        "no#": 7
    },
    {
        "title": "舞曲歌辭：白鳩辭",
        "author": "李白",
        "biography": "",
        "paragraphs": [
            "鏗鳴鐘，考朗鼓。歌白鳩，引拂舞。白鳩之白誰與鄰，",
            "首農政，鳴陽春。天子刻玉杖，鏤形賜耆人。",
            "白鷺亦白非純真，外潔其色心匪仁。闕五德，無司晨，",
            "鳳凰雖大聖，不願以為臣。"
        ],
        "notes": [
            ""
        ],
        "volume": "卷二十二",
        "no#": 8
    },
    {
        "title": "舞曲歌辭：獨漉篇",
        "author": "李白",
        "biography": "",
        "paragraphs": [
            "獨漉水中泥，水濁不見月。不見月尚可，水深行人沒。",
            "越鳥從南來，胡鷹亦北度。我欲彎弓向天射，",
            "雄劍掛壁，時時龍鳴。不斷犀象，繡澀苔生。國恥未雪，"
        ],
        "notes": [
            ""
        ],
        "volume": "卷二十二",
        "no#": 9
    },
    {
        "title": "舞曲歌辭：獨漉歌",
        "author": "王建",
        "biography": "",
        "paragraphs": [
            "獨獨漉漉，鼠食貓肉。",
            "烏日中，鶴露宿，黃河水直人心曲。"
        ],
        "notes": [
            ""
        ],
        "volume": "卷二十二",
        "no#": 10
    },
    {
        "title": "舞曲歌辭：白紵辭二首",
        "author": "崔國輔",
        "biography": "",
        "paragraphs": [
            "洛陽梨花落如霰，河陽桃葉生複齊。",
            "坐恐玉樓春欲盡，紅綿粉絮裛妝啼。",
            "董賢女弟在椒風，窈窕繁華貴後宮。",
            "璧帶金釭皆翡翠，一朝零落變成空。"
        ],
        "notes": [
            ""
        ],
        "volume": "卷二十二",
        "no#": 11
    },
    {
        "title": "舞曲歌辭：白紵辭二首",
        "author": "楊衡",
        "biography": "",
        "paragraphs": [
            "玉纓翠佩雜輕羅，香汗微漬朱顏酡。為君起唱白紵歌，",
            "躡珠履，步瓊筵。輕身起舞紅燭前，芳姿豔態妖且妍。",
            "回眸轉袖暗催弦，涼風蕭蕭流水急。月華泛豔紅蓮濕，"
        ],
        "notes": [
            ""
        ],
        "volume": "卷二十二",
        "no#": 12
    },
    {
        "title": "舞曲歌辭：白紵辭",
        "author": "李白",
        "biography": "",
        "paragraphs": [
            "揚清歌，發皓齒，北方佳人東鄰子。且吟白紵停淥水，",
            "玉顏滿堂樂未終，館娃日落歌吹蒙。",
            "月寒江清夜沉沉，美人一笑千黃金，垂羅舞縠揚哀音。",
            "郢中白雪且莫吟，子夜吳歌動君心。動君心，冀君賞，",
            "吳刀翦彩縫舞衣，明妝麗服奪春輝，揚眉轉袖若雪飛。",
            "傾城獨立世所稀，激楚結風醉忘歸。高堂月落燭已微，"
        ],
        "notes": [
            ""
        ],
        "volume": "卷二十二",
        "no#": 13
    },
    {
        "title": "舞曲歌辭：白紵歌二首",
        "author": "王建",
        "biography": "",
        "paragraphs": [
            "天河漫漫北斗粲，宮中烏啼知夜半。新縫白紵舞衣成，",
            "酒多夜長夜未曉，月明燈光兩相照，後庭歌聲更窈窕。",
            "館娃宮中春日暮，荔枝木瓜花滿樹。城頭烏棲休擊鼓，",
            "美人醉起無次第，墮釵遺佩滿中庭。此時但願可君意，"
        ],
        "notes": [
            ""
        ],
        "volume": "卷二十二",
        "no#": 14
    },
    {
        "title": "舞曲歌辭：白紵歌",
        "author": "張籍",
        "biography": "",
        "paragraphs": [
            "皎皎白紵白且鮮，將作春衫稱少年。裁縫長短不能定，",
            "衣裳著時寒食下，還把玉鞭鞭白馬。"
        ],
        "notes": [
            ""
        ],
        "volume": "卷二十二",
        "no#": 15
    },
    {
        "title": "舞曲歌辭：白紵歌",
        "author": "柳宗元",
        "biography": "",
        "paragraphs": [
            "翠帷雙卷出傾城，龍劍破匣霜月明。朱唇掩抑悄無聲，"
        ],
        "notes": [
            ""
        ],
        "volume": "卷二十二",
        "no#": 16
    },
    {
        "title": "舞曲歌辭：冬白紵歌",
        "author": "元稹",
        "biography": "",
        "paragraphs": [
            "吳宮夜長宮漏款，簾幕四垂燈焰暖。西施自舞王自管，",
            "共笑越王窮惴惴，夜夜抱冰寒不睡。"
        ],
        "notes": [
            ""
        ],
        "volume": "卷二十二",
        "no#": 17
    },
    {
        "title": "舞曲歌辭：霓裳辭十首",
        "author": "王建",
        "biography": "",
        "paragraphs": [
            "弟子部中留一色，聽風聽水作霓裳。",
            "散聲未足重來授，直到床前見上皇。",
            "中管五弦初半曲，遙教合上隔簾聽。",
            "一聲聲向天頭落，效得仙人夜唱經。",
            "自直梨園得出稀，更番上曲不教歸。",
            "一時跪拜霓裳徹，立地階前賜紫衣。",
            "旋翻新譜聲初足，除卻梨園未教人。",
            "宣與書家分手寫，中官走馬賜功臣。",
            "伴教霓裳有貴妃，從初直到曲成時。",
            "日長耳裏聞聲熟，拍數分毫錯總知。",
            "弦索摐摐隔彩雲，五更初發一山聞。",
            "武皇自送西王母，新換霓裳月色裙。",
            "敕賜宮人澡浴回，遙看美女院門開。",
            "一山星月霓裳動，好字先從殿裏來。",
            "傳呼法部按霓裳，新得承恩別作行。",
            "應是貴妃樓上看，內人舁下彩羅箱。",
            "朝元閣上山風起，夜聽霓裳玉露寒。",
            "宮女月中更替立，黃金梯滑並行難。",
            "知向華清年月滿，山頭山底種長生。",
            "去時留下霓裳曲，總是離宮別館聲。"
        ],
        "notes": [
            ""
        ],
        "volume": "卷二十二",
        "no#": 18
    },
    {
        "title": "舞曲歌辭：柘枝詞",
        "author": "不詳",
        "biography": "",
        "paragraphs": [
            "將軍奉命即須行，塞外領強兵。",
            "聞道烽煙動，腰間寶劍匣中鳴。"
        ],
        "notes": [
            ""
        ],
        "volume": "卷二十二",
        "no#": 19
    },
    {
        "title": "舞曲歌辭：柘枝詞三首",
        "author": "薛能",
        "biography": "",
        "paragraphs": [
            "同營三十萬，震鼓伐西羌。戰血粘秋草，征塵攪夕陽。",
            "歸來人不識，帝裏獨戎裝。",
            "懸軍征拓羯，內地隔蕭關。日色昆侖上，風聲朔漠間。",
            "何當千萬騎，颯颯貳師還。",
            "意氣成功日，春風起絮天。樓臺新邸第，歌舞小嬋娟。",
            "急破催搖曳，羅衫半脫肩。"
        ],
        "notes": [
            ""
        ],
        "volume": "卷二十二",
        "no#": 20
    },
    {
        "title": "舞曲歌辭：屈柘詞",
        "author": "溫庭筠",
        "biography": "",
        "paragraphs": [
            "楊柳縈橋綠，玫瑰拂地紅。繡衫金騕褭，花髻玉瓏璁。",
            "宿雨香潛潤，春流水暗通。畫樓初夢斷，晴日照湘風。"
        ],
        "notes": [
            ""
        ],
        "volume": "卷二十二",
        "no#": 21
    }
]